[
  {
    "name": "St. Patrick’s Cathedral",
    "image": "assets/armagh_cathedral2.png",
    "details": [
      "**Mass Times**",
      "Monday - Saturday - 10:00 AM",
      "Divine Mercy Hour - Mon, Wed, Fri - 3.00 PM",
      "Saturday - 6.30 PM (Sunday Vigil)",
      "Sunday - 11.00 AM, 12.30 PM & 5.30 PM",
      "**Holy Week**",
      "Mass - Mon to Wed - 10.00 AM",
      "Chrism Mass - Wednesday 7.00 PM",
      "**Holy Thursday**",
      "Mass of the Lord's Supper - 7.30 PM",
      "**Good Friday**",
      "The Lord's Passion - 3.00 PM",
      "**Holy Saturday**",
      "Morning Prayer - 10.00 AM",
      "Blessing of Easter Food - 1.00 PM",
      "Easter Vigil - 9.00 PM",
      "**Easter Sunday**",
      "Mass - 11.00 AM & 12.30 PM",
      "**Confessions**",
      "Friday after 10.00 AM Mass",
      "**Address**",
      "@@41 Cathedral Road, Armagh, BT61 7QX"
    ]
  },
  {
    "name": "St. Malachy’s Church",
    "image": "assets/st_malachys.png",
    "details": [
      "**Mass Times**",
      "Monday - Friday - 7.00 AM, 1.00 PM",
      "Mon, Weds, Fri - 7.30 PM",
      "Tues, Thurs - Prayer Service - 7.30 PM",
      "Sunday - 8:00 AM, 9.30 AM",
      "**Holy Week**",
      "Mass - Mon to Wed - 7.00 AM",
      "Novena Mass - Monday - 7.30 PM",
      "Penitential Service - Tuesday - 6.00 PM to 7.30 PM",
      "**Holy Thursday**",
      "Confessions - 12 noon",
      "**Good Friday**",
      "The Lord's Passion - 3.00 PM",
      "Stations of the Cross - 7.30 PM",
      "Prayer around the Cross - 9.00 PM",
      "**Easter Sunday**",
      "Mass - 8.00 AM & 9.30 PM",
      "**Confessions**",
      "Saturday - 12 noon",
      "",
      "**Address**",
      "@@54 Irish Street, Armagh, BT61 7EP"
    ]
  },
  {
    "name": "Church of the Immaculate Conception",
    "image": "assets/tullysaran.png",
    "details": [
      "**Mass Times**",
      "Sunday - 10.00 AM",
      "**Holy Week**",
      "Novena Mass - Monday - 7.30 PM",
      "**Holy Thursday**",
      "Mass of the Lord's Supper - 7.30 PM",
      "Altars of Repose close at 10.00 PM with Night Prayer",
      "**Good Friday**",
      "The Lord's Passion - 3.00 PM",
      "**Easter Sunday**",
      "Mass - 10.00 AM",
      "",
      "**Address**",
      "@@12 Milltown Road, Dungannon, BT71 7LJ"
    ]
  },
  {
    "name": "St. Colmcille’s Church",
    "image": "assets/knockaconey2.png",
    "details": [
      "**Mass Times**",
      "Saturday 6.00 PM (Sunday Vigil)",
      "**Holy Week**",
      "",
      "**Holy Thursday**",
      "Mass of the Lord's Supper - 7.30 PM",
      "Altars of Repose close at 10.00 PM with Night Prayer",
      "**Good Friday**",
      "The Lord's Passion - 7.30 PM",
      "**Holy Saturday**",
      "Easter Vigil - 6.00 PM",
      "**Easter Sunday**",
      "Mass - 10.00 AM",
      "",
      "**Address**",
      "@@18 Knockaconey Road, Armagh, BT61 8DU"
    ]
  }
]
